circrl/__init__.py
circrl/hooks.py
circrl/probing.py
circrl/rollouts.py
circrl-1.0.0.dist-info/METADATA
circrl-1.0.0.dist-info/WHEEL
circrl-1.0.0.dist-info/licenses/LICENSE
circrl-1.0.0.dist-info/RECORD
