Metadata-Version: 2.1
Name: circrl
Version: 1.0.0
Summary: Tools for applying circuits-style interpretability techniques to RL agents.
Project-URL: Homepage, https://github.com/montemac/circrl
Author-email: montemac <m.macdiarmid@gmail.com>
License-File: LICENSE
Classifier: License :: OSI Approved :: MIT License
Classifier: Operating System :: OS Independent
Classifier: Programming Language :: Python :: 3
Requires-Python: >=3.8
Requires-Dist: bidict>=0.22.1
Requires-Dist: blosc>=1.11.1
Requires-Dist: einops>=0.6.0
Requires-Dist: gym>=0.21.0
Requires-Dist: holoviews>=1.15.2
Requires-Dist: hvplot>=0.8.1
Requires-Dist: moviepy>=1.0.3
Requires-Dist: numpy>=1.22.1
Requires-Dist: pandas>=1.5.2
Requires-Dist: scikit-learn>=1.2.1
Requires-Dist: torch>=1.13.1
Requires-Dist: tqdm>=4.64.1
Requires-Dist: xarray>=2022.12.0
